pdxdisplay/__init__.py
pdxdisplay/bomtree.py
pdxdisplay/dbutils.py
pdxdisplay/getbomitem.py
pdxdisplay/getitem.py
pdxdisplay/homepage.py
pdxdisplay/partsmaster.py
pdxdisplay/upload.py
pdxdisplay/static/stylesheets/style.css
pdxdisplay/templates/bomtree.html
pdxdisplay/templates/error.html
pdxdisplay/templates/error_insert.html
pdxdisplay/templates/footer.html
pdxdisplay/templates/getbomitem.html
pdxdisplay/templates/getitem.html
pdxdisplay/templates/header.html
pdxdisplay/templates/homepage.html
pdxdisplay/templates/partsmaster.html
pdxdisplay-0.0.1a2.dist-info/DESCRIPTION.rst
pdxdisplay-0.0.1a2.dist-info/METADATA
pdxdisplay-0.0.1a2.dist-info/RECORD
pdxdisplay-0.0.1a2.dist-info/WHEEL
pdxdisplay-0.0.1a2.dist-info/entry_points.txt
pdxdisplay-0.0.1a2.dist-info/metadata.json
pdxdisplay-0.0.1a2.dist-info/top_level.txt
