Metadata-Version: 2.0
Name: pdxdisplay
Version: 0.0.1a2
Summary: Simple web application for viewing PDX (Product Data eXchange) XML files
Home-page: https://github.com/sid5432/pdxdisplay
Author: Sidney Li
Author-email: sidneyli5432@gmail.com
License: UNKNOWN
Keywords: PDX package data exchange IPC IPC-2571 IPC-2570 Flask database postgreSQL sqlite3
Platform: UNKNOWN
Classifier: Development Status :: 3 - Alpha
Classifier: Intended Audience :: Manufacturing
Classifier: Topic :: Utilities
Classifier: License :: OSI Approved :: Apache Software License
Classifier: Programming Language :: Python :: 2
Classifier: Programming Language :: Python :: 2.7
Classifier: Programming Language :: Python :: 3
Classifier: Programming Language :: Python :: 3.4
Classifier: Programming Language :: Python :: 3.5
Classifier: Programming Language :: Python :: 3.6
Requires-Dist: flask
Requires-Dist: pypdx
